mtrec/__init__.py
mtrec/functions/__init__.py
mtrec/functions/feature_column.py
mtrec/functions/utils.py
mtrec/layers/__init__.py
mtrec/layers/core.py
mtrec/models/__init__.py
mtrec/models/mmoe.py
mtrec-0.0.1.dist-info/LICENSE.txt
mtrec-0.0.1.dist-info/METADATA
mtrec-0.0.1.dist-info/WHEEL
mtrec-0.0.1.dist-info/top_level.txt
mtrec-0.0.1.dist-info/RECORD
