Metadata-Version: 2.1
Name: mtrec
Version: 0.0.1
Summary: A simple package about multi-task recommendation
Home-page: https://github.com/ZiyaoGeng/MTRec
Author: Ziyao Geng
Author-email: zggzy1996@163.com
License: Apache-2.0
Platform: UNKNOWN
Classifier: Programming Language :: Python :: 3
Classifier: License :: OSI Approved :: MIT License
Classifier: Operating System :: OS Independent
Requires-Python: >=3.6
